datasus_fetcher/__init__.py
datasus_fetcher/cli.py
datasus_fetcher/constants.py
datasus_fetcher/fetcher.py
datasus_fetcher/meta.py
datasus_fetcher/remote_names.py
datasus_fetcher/slicer.py
datasus_fetcher/storage.py
datasus_fetcher-0.4.1.dist-info/LICENSE
datasus_fetcher-0.4.1.dist-info/METADATA
datasus_fetcher-0.4.1.dist-info/WHEEL
datasus_fetcher-0.4.1.dist-info/entry_points.txt
datasus_fetcher-0.4.1.dist-info/top_level.txt
datasus_fetcher-0.4.1.dist-info/RECORD
