Metadata-Version: 2.2
Name: datasus-fetcher
Version: 0.4.1
Summary: Downloader of DATASUS raw data files
Author-email: Daniel Komesu <danielkomesu@gmail.com>
License: MIT
Keywords: data,open data,data fetcher,health,datasus,microdata
Requires-Python: >=3.10
License-File: LICENSE
